setup.cfg
setup.py
elasticity/__init__.py
elasticity.egg-info/PKG-INFO
elasticity.egg-info/SOURCES.txt
elasticity.egg-info/dependency_links.txt
elasticity.egg-info/requires.txt
elasticity.egg-info/top_level.txt
scripts/elasticity