Metadata-Version: 1.1
Name: elasticity
Version: 0.3
Summary: Python based command line tool for managing ElasticSearch clusters.
Home-page: https://github.com/Cheers-Dev/elasticity
Author: Brian C. Dilley - Flipagram
Author-email: brian@flipagram.com
License: UNKNOWN
Download-URL: https://github.com/Cheers-Dev/elasticity
Platform: any
Classifier: Intended Audience :: Developers
